odoo/addons/product_form_account_move_line_link/README.rst
odoo/addons/product_form_account_move_line_link/__init__.py
odoo/addons/product_form_account_move_line_link/__manifest__.py
odoo/addons/product_form_account_move_line_link/i18n/product_form_account_move_line_link.pot
odoo/addons/product_form_account_move_line_link/models/__init__.py
odoo/addons/product_form_account_move_line_link/models/product_product.py
odoo/addons/product_form_account_move_line_link/models/product_template.py
odoo/addons/product_form_account_move_line_link/readme/CONTRIBUTORS.rst
odoo/addons/product_form_account_move_line_link/readme/DESCRIPTION.rst
odoo/addons/product_form_account_move_line_link/readme/USAGE.rst
odoo/addons/product_form_account_move_line_link/static/description/icon.png
odoo/addons/product_form_account_move_line_link/static/description/index.html
odoo/addons/product_form_account_move_line_link/views/account_move_line_views.xml
odoo/addons/product_form_account_move_line_link/views/product_product_views.xml
odoo/addons/product_form_account_move_line_link/views/product_template_views.xml
odoo13_addon_product_form_account_move_line_link-13.0.1.0.1.dev3.dist-info/METADATA
odoo13_addon_product_form_account_move_line_link-13.0.1.0.1.dev3.dist-info/WHEEL
odoo13_addon_product_form_account_move_line_link-13.0.1.0.1.dev3.dist-info/top_level.txt
odoo13_addon_product_form_account_move_line_link-13.0.1.0.1.dev3.dist-info/RECORD
